genpipe/__init__.py
genpipe/genpipe.py
genpipe/operations.py
genpipe/protocol.py
genpipe-0.1.0.dist-info/LICENSE
genpipe-0.1.0.dist-info/WHEEL
genpipe-0.1.0.dist-info/METADATA
genpipe-0.1.0.dist-info/RECORD
